etc/gen2-connector/defaults.yaml
etc/gen2-connector/example-minimal.yaml
gen2/__init__.py
gen2/node_provider.py
gen2_connector-1.0.0b67.data/scripts/vpc-config
gen2_connector-1.0.0b67.dist-info/LICENSE
gen2_connector-1.0.0b67.dist-info/METADATA
gen2_connector-1.0.0b67.dist-info/WHEEL
gen2_connector-1.0.0b67.dist-info/top_level.txt
gen2_connector-1.0.0b67.dist-info/RECORD
