Metadata-Version: 2.1
Name: gen2-connector
Version: 1.0.0b67
Summary: Ray gen2 node provider
Home-page: https://github.com/project-codeflare/gen2-connector
Author: kpavel, cohen-j-omer
Author-email: omer.cohen@ibm.com
Classifier: Programming Language :: Python :: 3
Requires-Python: >=3.6
License-File: LICENSE
Requires-Dist: ibm-vpc
